streamsx/objectstorage/__init__.py
streamsx/objectstorage/_objectstorage.py
streamsx.objectstorage-1.5.6.dist-info/LICENSE.txt
streamsx.objectstorage-1.5.6.dist-info/METADATA
streamsx.objectstorage-1.5.6.dist-info/WHEEL
streamsx.objectstorage-1.5.6.dist-info/top_level.txt
streamsx.objectstorage-1.5.6.dist-info/RECORD
