Metadata-Version: 2.1
Name: streamsx.objectstorage
Version: 1.5.6
Summary: Object Storage integration for IBM Streams
Home-page: https://github.com/IBMStreams/streamsx.objectstorage
Author: IBM Streams @ github.com
Author-email: hegermar@de.ibm.com
License: Apache License - Version 2.0
Keywords: streams,ibmstreams,streaming,analytics,streaming-analytics,cos,objectstorage
Platform: UNKNOWN
Classifier: Development Status :: 5 - Production/Stable
Classifier: License :: OSI Approved :: Apache Software License
Classifier: Programming Language :: Python :: 3
Classifier: Programming Language :: Python :: 3.5
Classifier: Programming Language :: Python :: 3.6
Classifier: Programming Language :: Python :: 3.7
Requires-Dist: streamsx (>=1.12.10)
Requires-Dist: streamsx.toolkits
